mytlc/__init__.py
mytlc/constants.py
mytlc/logger.py
mytlc/build_dataset/__init__.py
mytlc/build_dataset/dataset_builder.py
mytlc/catalog/__init__.py
mytlc/catalog/catalog_manager.py
mytlc/check_dataset/__init__.py
mytlc/check_dataset/check_dataset.py
mytlc/download/__init__.py
mytlc/download/era5_downloader.py
mytlc/download/hadisd_downloader.py
mytlc/search/__init__.py
mytlc/search/search.py
mytlc/templates/__init__.py
mytlc/templates/content_metadata_template.json
mytlc/templates/general_metadata_schema.json
mytlc/templates/general_metadata_template.json
mytlc/tests/__init__.py
mytlc/tests/test_dataset_builder.py
mytlc/tests/test_era5_downloader.py
mytlc/tests/test_search.py
mytlc/tests/data/test_dataset_builder_data/ERA5_data/2023_01_2m_temperature.nc
mytlc/tests/data/test_dataset_builder_data/ERA5_data/checksums_generated.txt
mytlc/tests/data/test_dataset_builder_data/ERA5_data/general_metadata.json
mytlc/tests/data/test_dataset_builder_data/HadISD_data/WMO_000000-029999.tar.gz
mytlc/tests/data/test_dataset_builder_data/HadISD_data/checksums.txt
mytlc/tests/data/test_dataset_builder_data/HadISD_data/checksums_generated.txt
mytlc/tests/data/test_dataset_builder_data/HadISD_data/general_metadata.json
mytlc/tests/data/test_dataset_builder_data/HadISD_data/hadisd_station_info_v341_202405p.txt
mytlc/tests/data/test_search_data/catalog.json
mytlc/tests/data/test_search_data/ERA5_test_01.00.00/2023_01_2m_temperature.nc
mytlc/tests/data/test_search_data/ERA5_test_01.00.00/2023_01_2m_temperature_content_metadata.json
mytlc/tests/data/test_search_data/ERA5_test_01.00.00/checksums_generated.txt
mytlc/tests/data/test_search_data/ERA5_test_01.00.00/general_metadata.json
mytlc/tests/data/test_search_data/ERA5_test_01.00.00/release_notes.md
mytlc/utils/__init__.py
mytlc/utils/metadata.py
mytlc-0.2.0.dist-info/LICENSE.txt
mytlc-0.2.0.dist-info/METADATA
mytlc-0.2.0.dist-info/WHEEL
mytlc-0.2.0.dist-info/top_level.txt
mytlc-0.2.0.dist-info/RECORD
